pyeuler
